setup.py
mybit/__init__.py
mybit/utils.py
mybit/bit_modules/__init__.py
mybit/bit_modules/base32.py
mybit/bit_modules/base58.py
mybit/bit_modules/constants.py
mybit/bit_modules/crypto.py
mybit/bit_modules/curve.py
mybit/bit_modules/exceptions.py
mybit/bit_modules/format.py
mybit/bit_modules/keygen.py
mybit/bit_modules/transaction.py
mybit/bit_modules/utils.py
mybit/bit_modules/wallet.py
mybit/bit_modules/network/__init__.py
mybit/bit_modules/network/fees.py
mybit/bit_modules/network/meta.py
mybit/bit_modules/network/rates.py
mybit/bit_modules/network/services.py
mybit/network/__init__.py
mybit/network/electrum_client.py
mybit/network/electrum_service.py
mybit/network/servers.json
mybit/transactions/__init__.py
mybit/transactions/base32.py
mybit/transactions/script_hash_converter.py
mybit/transactions/transaction_serializer.py
mybit/transactions/transactions.py
mybit/transactions/tx_objects.py
mybit/transactions/unspent.py
mybit/transactions/utxo_selector.py
mybit/wallet/__init__.py
mybit/wallet/base_key.py
mybit/wallet/unspent.py
mybit/wallet/wallet_base.py
mybit/wallet/wallet_factory.py
mybit/wallet/cryptos/__init__.py
mybit/wallet/cryptos/bitcoin.py
mybit/wallet/cryptos/crypto_constants.py
mybit/wallet/cryptos/crypto_format.py
mybit/wallet/cryptos/crypto_info.py
mybit/wallet/cryptos/dogecoin.py
mybit/wallet/cryptos/litecoin.py
mybit_module.egg-info/PKG-INFO
mybit_module.egg-info/SOURCES.txt
mybit_module.egg-info/dependency_links.txt
mybit_module.egg-info/requires.txt
mybit_module.egg-info/top_level.txt