Metadata-Version: 2.1
Name: mybit-module
Version: 0.1.0
Summary: A library for handling multiple cryptocurrencies
Author: Jhon Doe
Requires-Python: >=3.6
Requires-Dist: asn1crypto==1.5.1
Requires-Dist: certifi==2024.8.30
Requires-Dist: cffi==1.17.0
Requires-Dist: charset-normalizer==3.3.2
Requires-Dist: coincurve==20.0.0
Requires-Dist: idna==3.8
Requires-Dist: pycparser==2.22
Requires-Dist: requests==2.32.3
Requires-Dist: urllib3==2.2.2
